Custom_bar/__init__.py
Custom_bar/main.py
custom_bar-1.0.2.dist-info/licenses/LICENSE
custom_bar-1.0.2.dist-info/METADATA
custom_bar-1.0.2.dist-info/WHEEL
custom_bar-1.0.2.dist-info/top_level.txt
custom_bar-1.0.2.dist-info/RECORD
