Metadata-Version: 2.4
Name: Custom_Bar
Version: 1.0.2
Summary: A module for custom loading bar
Author-email: Grivy16 <grivy16public@gmail.com>
License: MIT
Project-URL: Homepage, https://github.com/Grivy16/Python-Loading-bar
Requires-Python: >=3.8
License-File: LICENSE
Dynamic: license-file
